<annotation>
	<folder>data_images</folder>
	<filename>video4_11_jpg.rf.c7f61bb73052c54d1c3e288c0a675111.jpg</filename>
	<path>E:\Yolo_chicken_health\datapreparation\data_images\video4_11_jpg.rf.c7f61bb73052c54d1c3e288c0a675111.jpg</path>
	<source>
		<database>Unknown</database>
	</source>
	<size>
		<width>416</width>
		<height>416</height>
		<depth>3</depth>
	</size>
	<segmented>0</segmented>
	<object>
		<name>Unhealthy</name>
		<pose>Unspecified</pose>
		<truncated>0</truncated>
		<difficult>0</difficult>
		<bndbox>
			<xmin>151</xmin>
			<ymin>104</ymin>
			<xmax>297</xmax>
			<ymax>408</ymax>
		</bndbox>
	</object>
	<object>
		<name>Unhealthy</name>
		<pose>Unspecified</pose>
		<truncated>0</truncated>
		<difficult>0</difficult>
		<bndbox>
			<xmin>3</xmin>
			<ymin>126</ymin>
			<xmax>160</xmax>
			<ymax>400</ymax>
		</bndbox>
	</object>
</annotation>
