<annotation>
	<folder>data_images</folder>
	<filename>z9.jpeg</filename>
	<path>E:\Yolo_chicken_health\datapreparation\data_images\z9.jpeg</path>
	<source>
		<database>Unknown</database>
	</source>
	<size>
		<width>848</width>
		<height>565</height>
		<depth>3</depth>
	</size>
	<segmented>0</segmented>
	<object>
		<name>Healthy</name>
		<pose>Unspecified</pose>
		<truncated>0</truncated>
		<difficult>0</difficult>
		<bndbox>
			<xmin>179</xmin>
			<ymin>162</ymin>
			<xmax>440</xmax>
			<ymax>549</ymax>
		</bndbox>
	</object>
	<object>
		<name>Healthy</name>
		<pose>Unspecified</pose>
		<truncated>0</truncated>
		<difficult>0</difficult>
		<bndbox>
			<xmin>364</xmin>
			<ymin>168</ymin>
			<xmax>629</xmax>
			<ymax>363</ymax>
		</bndbox>
	</object>
</annotation>
